MANIFEST.in
README.rst
setup.cfg
setup.py
autocomplete/__init__.py
autocomplete/helpers.py
autocomplete/models.py
autocomplete.egg-info/PKG-INFO
autocomplete.egg-info/SOURCES.txt
autocomplete.egg-info/dependency_links.txt
autocomplete.egg-info/not-zip-safe
autocomplete.egg-info/requires.txt
autocomplete.egg-info/top_level.txt
bin/autocomplete_server.py