Metadata-Version: 1.0
Name: autocomplete
Version: 0.0.102
Summary: tiny 'autocomplete' tool using a "hidden markov model"
Home-page: https://github.com/rodricios/autocomplete
Author: Rodrigo Palacios
Author-email: rodrigopala91@gmail.com
License: MIT
Keywords: autocomplete autosuggest suggest complete spell spellsuggest                 hidden markov model HMM hmm markov chain                 automatic spelling word suggest machine learning ai text                 conditional probability model probabilistic perspective                 Rodrigo Palacios rodrigo palacios im-rodrigo im_rodrigo                 rodricios
Platform: UNKNOWN
